gopac/__init__.py
gopac/exceptions.py
gopac/gopac.py
gopac/extension/gopaccli.cpython-37m-darwin.so
pygopac-0.1.0.dist-info/METADATA
pygopac-0.1.0.dist-info/WHEEL
pygopac-0.1.0.dist-info/dependency_links.txt
pygopac-0.1.0.dist-info/top_level.txt
pygopac-0.1.0.dist-info/RECORD
