Metadata-Version: 2.1
Name: pygopac
Version: 0.1.0
Summary: Python library to parse proxy auto-config (PAC) files.
Home-page: https://bitbucket.org/alex925/py-gopac/src/master/
Author: Aleksey Petrunnik
Author-email: petrunnik.a@mail.ru
License: UNKNOWN
Platform: UNKNOWN
Requires-Dist: requests (>=2.18.4)
